stuntcat/__init__.py
stuntcat/__main__.py
stuntcat/cli.py
stuntcat/game.py
stuntcat/gifmaker.py
stuntcat/main.py
stuntcat/pyg.py
stuntcat/resources.py
stuntcat/__pycache__/__init__.cpython-311.pyc
stuntcat/__pycache__/game.cpython-311.pyc
stuntcat/__pycache__/gifmaker.cpython-311.pyc
stuntcat/__pycache__/resources.cpython-311.pyc
stuntcat/data/aneasterchicken.txt
stuntcat/data/images/background.png
stuntcat/data/images/cat.png
stuntcat/data/images/cat_grey_left_200x143.png
stuntcat/data/images/cat_grey_right_200x143.png
stuntcat/data/images/cat_unicycle.png
stuntcat/data/images/cat_unicycle1.png
stuntcat/data/images/cat_unicycle2.png
stuntcat/data/images/cat_unicycle3.png
stuntcat/data/images/cat_unicycle4.png
stuntcat/data/images/fish.png
stuntcat/data/images/fish_green.png
stuntcat/data/images/fish_red.png
stuntcat/data/images/fish_yellow.png
stuntcat/data/images/foot.png
stuntcat/data/images/foot_part.png
stuntcat/data/images/intro_screen.png
stuntcat/data/images/ring.png
stuntcat/data/images/seat.png
stuntcat/data/images/shark.png
stuntcat/data/images/shark_laser.png
stuntcat/data/images/wheel.png
stuntcat/data/images/yarnball.png
stuntcat/data/maps/untitled.tmx
stuntcat/data/sounds/applause.ogg
stuntcat/data/sounds/boing1.ogg
stuntcat/data/sounds/boing2.ogg
stuntcat/data/sounds/boing3.ogg
stuntcat/data/sounds/boo.ogg
stuntcat/data/sounds/cat_crash.ogg
stuntcat/data/sounds/cat_jump-old.ogg
stuntcat/data/sounds/cat_jump.ogg
stuntcat/data/sounds/cat_laser_2.ogg
stuntcat/data/sounds/cat_laser_3.ogg
stuntcat/data/sounds/cat_meow01.ogg
stuntcat/data/sounds/cat_meow02.ogg
stuntcat/data/sounds/cat_meow03.ogg
stuntcat/data/sounds/cat_shot.ogg
stuntcat/data/sounds/cat_wheel.ogg
stuntcat/data/sounds/default_shark.ogg
stuntcat/data/sounds/eatfish.ogg
stuntcat/data/sounds/foot_elephant.ogg
stuntcat/data/sounds/ict_0026.ogg
stuntcat/data/sounds/mainmenu.ogg
stuntcat/data/sounds/shark_appear.ogg
stuntcat/data/sounds/shark_attacks-old.ogg
stuntcat-0.2.4.dist-info/LICENSE.txt
stuntcat-0.2.4.dist-info/METADATA
stuntcat-0.2.4.dist-info/WHEEL
stuntcat-0.2.4.dist-info/entry_points.txt
stuntcat-0.2.4.dist-info/top_level.txt
stuntcat-0.2.4.dist-info/RECORD
