Metadata-Version: 2.1
Name: stuntcat
Version: 0.2.4
Summary: Stuntcat is the first pygame 2 community game.
Home-page: https://github.com/pygame/stuntcat
Author: stuntcat team
Author-email: stuntcat@pygame.org
Maintainer: stuntcat team
Maintainer-email: stuntcat@pygame.org
License: LGPL
Classifier: Development Status :: 4 - Beta
Classifier: License :: OSI Approved :: GNU Lesser General Public License v2 or later (LGPLv2+)
Classifier: Programming Language :: Python :: 2
Classifier: Programming Language :: Python :: 2.7
Classifier: Programming Language :: Python :: 3
Classifier: Programming Language :: Python :: 3.4
Classifier: Programming Language :: Python :: 3.6
Classifier: Programming Language :: Python :: 3.7
Classifier: Programming Language :: Python :: 3.8
Classifier: Programming Language :: Python :: 3.9
Classifier: Programming Language :: Python :: 3.10
Classifier: Programming Language :: Python :: 3.11
Classifier: Programming Language :: Python :: 3.12
Classifier: Topic :: Software Development :: Libraries :: pygame
Classifier: Topic :: Games/Entertainment :: Arcade
License-File: LICENSE.txt
Requires-Dist: pygame
Requires-Dist: pyscroll
Requires-Dist: pytmx
Requires-Dist: thorpy
Requires-Dist: pymunk >=5.4.2
Requires-Dist: typing ; python_version < "3.5"
